setup.py
smart_clicker/__init__.py
smart_clicker/core.py
smart_clicker/snipper.py
smart_clicker.egg-info/PKG-INFO
smart_clicker.egg-info/SOURCES.txt
smart_clicker.egg-info/dependency_links.txt
smart_clicker.egg-info/requires.txt
smart_clicker.egg-info/top_level.txt