Metadata-Version: 2.1
Name: smart-clicker
Version: 1.1.6
Summary: A simple screen automation tool with hotkey snapshot capability.淘宝:阳阳软件市场
Author: jiaobenxiaozi
Author-email: 183732521@qq.com
